MANIFEST.in
README.md
setup.cfg
setup.py
PyDNET.egg-info/PKG-INFO
PyDNET.egg-info/SOURCES.txt
PyDNET.egg-info/dependency_links.txt
PyDNET.egg-info/requires.txt
PyDNET.egg-info/top_level.txt
data/test-fukui-tepco.yaml
data/test.yaml
data/test-fukui-tepco/LNewSL.dat
data/test-fukui-tepco/LNewZ.dat
data/test-fukui-tepco/SWed.dat
data/test-fukui-tepco/root.dat
data/test-fukui-tepco/sw_list.dat
dnet/__init__.py
dnet/configset.py
dnet/converter.py
dnet/network.py
dnet/release.py
dnet/unionfind.py
dnet/util.py
dnet/test/__init__.py
dnet/test/network.py
doc/example_nw.png
doc/theory.pdf