Metadata-Version: 1.1
Name: PyDNET
Version: 1.0
Summary: Distribution Network Evaluation Tool
Home-page: https://github.com/takemaru/dnet
Author: Takeru Inoue
Author-email: takeru.inoue@gmail.com
License: MIT
Keywords: power distribution network,optimization,graph
Platform: UNKNOWN
Classifier: Development Status :: 4 - Beta
Classifier: Intended Audience :: Science/Research
Classifier: License :: OSI Approved :: MIT License
Classifier: Operating System :: POSIX :: Linux
Classifier: Operating System :: POSIX :: BSD :: FreeBSD
Classifier: Operating System :: MacOS :: MacOS X
Classifier: Programming Language :: Python :: 2.7
Classifier: Programming Language :: Python :: 2
Classifier: Programming Language :: Python :: 3.4
Classifier: Programming Language :: Python :: 3.5
Classifier: Programming Language :: Python :: 3.6
Classifier: Programming Language :: Python :: 3
Classifier: Topic :: Scientific/Engineering
